{
  "title": "ุชูุงูู ูุงุฌูุงุช ุจุฑูุฌุฉ ุงูุชุทุจููุงุช (API)",
  "slug": "api-integration",
  "description": "ูููู ุจุชูุตูู ุชุทุจููุงุชู ุจุฎุฏูุงุช ุงูุทุฑู ุงูุซุงูุซ ูุชูุณูุน ูุธุงุฆููุง.",
  "icon": "๐",
  "details": {
    "overview": "ูููู ุจุฏูุฌ ูุงุฌูุงุช ุจุฑูุฌุฉ ุงูุชุทุจููุงุช (APIs) ูุชูุณูุน ูุฏุฑุงุช ุชุทุจููุงุชู.",
    "features": [
      "ุงูุชูุงูู ูุน ุฎุฏูุงุช ุงูุฏูุน ูุซู Stripe ูPayPal.",
      "ุงูุงุชุตุงู ุจูุณุงุฆู ุงูุชูุงุตู ุงูุงุฌุชูุงุนู ูุซู Facebook ูTwitter ูInstagram.",
      "ุฃุชูุชุฉ ุงูุนูููุงุช ุจุงุณุชุฎุฏุงู ูุงุฌูุงุช ุจุฑูุฌุฉ ุงูุชุทุจููุงุช ุงููุฎุตุตุฉ."
    ],
    "technologies": [
      "REST",
      "GraphQL",
      "Postman",
      "OAuth"
    ],
    "objective": "ุฅุฐุง ูุงู ูุฏูู ูู ุชูุตูู ุชุทุจููู ุจุฎุฏูุงุช ุงูุทุฑู ุงูุซุงูุซ ูุชูุณูุน ูุธุงุฆููุ ูููููุง ูุณุงุนุฏุชู ูู ุงูุชูุงูู ุงููุนุงู ูุงูุขูู ููุงุฌูุงุช ุจุฑูุฌุฉ ุงูุชุทุจููุงุช."
  },
  "metaDescription": "ูุณูุน ูุธุงุฆู ุชุทุจููู ูุน ุฎุฏูุงุชูุง ูู ุชูุงูู ูุงุฌูุงุช ุจุฑูุฌุฉ ุงูุชุทุจููุงุช. ูููู ุจุชูุตูู ุชุทุจููุงุชู ุจุฎุฏูุงุช ุงูุทุฑู ุงูุซุงูุซ ุจุณูุงุณุฉ ูุฃูุงู.",
  "schema": {
    "@context": "https://schema.org",
    "@type": "Service",
    "name": "ุชูุงูู ูุงุฌูุงุช ุจุฑูุฌุฉ ุงูุชุทุจููุงุช (API)",
    "description": "ูููู ุจุชูุตูู ุชุทุจููุงุชู ุจุฎุฏูุงุช ุงูุทุฑู ุงูุซุงูุซ ูุชูุณูุน ูุธุงุฆููุง.",
    "serviceType": "ุชูุงูู ูุงุฌูุงุช ุจุฑูุฌุฉ ุงูุชุทุจููุงุช",
    "provider": {
      "@type": "Organization",
      "name": "ุงุณู ุดุฑูุชู"
    },
    "areaServed": {
      "@type": "Country",
      "name": "ุงูุฏูู ุงูุชู ุชุฎุฏููุง"
    }
  }
}
